ternary/__init__.py
ternary/colormapping.py
ternary/coordinates.py
ternary/heatmapping.py
ternary/helpers.py
ternary/lines.py
ternary/plotting.py
ternary/ternary_axes_subplot.py
python_ternary-1.0.8.dist-info/LICENSE
python_ternary-1.0.8.dist-info/METADATA
python_ternary-1.0.8.dist-info/WHEEL
python_ternary-1.0.8.dist-info/top_level.txt
python_ternary-1.0.8.dist-info/RECORD
